logutil/__init__.py
logutil/console_handler.py
logutil/datadog_handler.py
logutil/file_handler.py
logutil/formatter.py
logutil/levels.py
logutil/logger.py
logutil/message_queue.py
bfg_logutil-0.2.2.dist-info/METADATA
bfg_logutil-0.2.2.dist-info/WHEEL
bfg_logutil-0.2.2.dist-info/licenses/LICENSE
bfg_logutil-0.2.2.dist-info/RECORD
