Metadata-Version: 2.4
Name: bfg-logutil
Version: 0.2.2
Summary: A python logging library that writes to console, local file and datadog
Author-email: leizha <8961794+leizha@users.noreply.github.com>
License-File: LICENSE
Requires-Python: >=3.10
Requires-Dist: requests
